setup.cfg
setup.py
docs/HISTORY.txt
docs/readme.txt
js/__init__.py
js.hogan.egg-info/PKG-INFO
js.hogan.egg-info/SOURCES.txt
js.hogan.egg-info/dependency_links.txt
js.hogan.egg-info/entry_points.txt
js.hogan.egg-info/namespace_packages.txt
js.hogan.egg-info/not-zip-safe
js.hogan.egg-info/requires.txt
js.hogan.egg-info/top_level.txt
js/hogan/__init__.py
js/hogan/release.py
js/hogan/js/hogan-3.0.0.amd.js
js/hogan/js/hogan-3.0.0.common.js
js/hogan/js/hogan-3.0.0.js
js/hogan/js/hogan-3.0.0.min.amd.js
js/hogan/js/hogan-3.0.0.min.common.js
js/hogan/js/hogan-3.0.0.min.js
js/hogan/js/hogan-3.0.0.min.mustache.js
js/hogan/js/hogan-3.0.0.mustache.js
js/hogan/js/hogan.template-3.0.0.amd.js
js/hogan/js/hogan.template-3.0.0.common.js
js/hogan/js/hogan.template-3.0.0.js
js/hogan/js/hogan.template-3.0.0.min.amd.js
js/hogan/js/hogan.template-3.0.0.min.common.js
js/hogan/js/hogan.template-3.0.0.min.js
js/hogan/js/hogan.template-3.0.0.min.mustache.js
js/hogan/js/hogan.template-3.0.0.mustache.js