Metadata-Version: 1.1
Name: js.hogan
Version: 3.0.0.3
Summary: Fanstatic Twitter's Hogan.js
Home-page: http://www.merchise.org
Author: Merchise Autrement
Author-email: UNKNOWN
License: GPL
Keywords: fanstatic,hogan
Platform: UNKNOWN
Classifier: Programming Language :: Python :: 2.7
Classifier: Development Status :: 5 - Production/Stable
Classifier: Topic :: Software Development :: Libraries
